{
  "taskId": "par_256_phase3_track_Playwright_or_other_appropriate_tooling_frontend_build_queue_workboard_preview_pocket_and_selected_anchor_preservation",
  "cases": [
    {
      "caseId": "rank_shift_preserve_selected",
      "sourceQueue": "recommended",
      "anchorTaskId": "task-311",
      "expectedVisibleState": "QueueChangeBatch preserves task-311 at the pinned position until explicit apply."
    },
    {
      "caseId": "apply_batch_then_reorder_background",
      "sourceQueue": "recommended",
      "anchorTaskId": "task-311",
      "expectedVisibleState": "Explicit apply changes background order while task-311 remains the selected anchor."
    },
    {
      "caseId": "search_hidden_stub",
      "sourceQueue": "recommended",
      "anchorTaskId": "task-412",
      "expectedVisibleState": "QueueAnchorStub surfaces search_hidden and clears search without dropping shell continuity."
    },
    {
      "caseId": "approval_lane_stub",
      "sourceQueue": "returned-evidence",
      "anchorTaskId": "task-208",
      "expectedVisibleState": "QueueAnchorStub surfaces moved_to_approvals and offers a one-step lane switch."
    },
    {
      "caseId": "reassigned_stub",
      "sourceQueue": "recommended",
      "anchorTaskId": "task-118",
      "expectedVisibleState": "QueueAnchorStub surfaces moved_to_changed rather than silently selecting a neighbor row."
    },
    {
      "caseId": "task_open_queue_visibility",
      "sourceQueue": "callback-follow-up",
      "anchorTaskId": "task-412",
      "expectedVisibleState": "Queue remains visible and the preview pocket shifts to task_open while the primary pane opens the task."
    }
  ]
}
