{
  "gapId": "PHASE4_INTERFACE_GAP_BOOKING_ARTIFACT_PARITY_VIEW",
  "taskId": "par_303_phase4_track_Playwright_or_other_appropriate_tooling_frontend_build_accessibility_and_artifact_parity_for_booking_documents",
  "status": "local_contract_created",
  "createdAt": "2026-04-20",
  "problem": "The repository had no booking-specific artifact parity digest view spanning receipt summary, print posture, calendar payload, and handoff metadata.",
  "closure": "Task 303 adds BookingArtifactParityView as the thinnest lawful parity-evidence surface for booking artifacts.",
  "remainingRisk": "Parity evidence remains frontend-local until a broader shared artifact digest contract adopts the same booking markers."
}
